containers/AVLTree.py
containers/BST.py
containers/BinaryTree.py
containers/Heap.py
containers/fibonacci.py
containers/range.py
containers/unicode.py
dwang862_containers-1.0.0.dist-info/DESCRIPTION.rst
dwang862_containers-1.0.0.dist-info/METADATA
dwang862_containers-1.0.0.dist-info/RECORD
dwang862_containers-1.0.0.dist-info/WHEEL
dwang862_containers-1.0.0.dist-info/metadata.json
dwang862_containers-1.0.0.dist-info/top_level.txt
