Metadata-Version: 2.0
Name: dwang862-containers
Version: 1.0.0
Summary: Contains fibonacci, range, unicode, BinaryTree, BST, AVLTree, Heap
Home-page: https://github.com/dwang862/containers-hw
Author: Daniel Wang
Author-email: dwang22@cmc.edu
License: MIT
Platform: UNKNOWN
Classifier: License :: OSI Approved :: MIT License
Classifier: Programming Language :: Python :: 3
Classifier: Programming Language :: Python :: 3.7
